vcf_generator/__init__.py
vcf_generator/__main__.py
vcf_generator/address.py
vcf_generator/contact.py
vcf_generator/email.py
vcf_generator/gen_contacts.py
vcf_generator/gen_vcards.py
vcf_generator/phone_number.py
vcf_generator-1.1.7.dist-info/LICENSE
vcf_generator-1.1.7.dist-info/METADATA
vcf_generator-1.1.7.dist-info/WHEEL
vcf_generator-1.1.7.dist-info/entry_points.txt
vcf_generator-1.1.7.dist-info/RECORD
