Metadata-Version: 2.1
Name: vcf-generator
Version: 1.1.7
Summary: A simple VCF generator. Generate VCF files with random data.
Home-page: https://github.com/talk2bryan/vcf-generator
License: MIT
Keywords: vcf,generator,vcard,contacts,faker,python
Author: Bryan Wodi
Author-email: pypi.envy443@dralias.com
Requires-Python: >=3.10,<4.0
Classifier: License :: OSI Approved :: MIT License
Classifier: Programming Language :: Python :: 3
Classifier: Programming Language :: Python :: 3.10
Classifier: Programming Language :: Python :: 3.11
Classifier: Programming Language :: Python :: 3.12
Requires-Dist: faker (>=24.4.0,<25.0.0)
Requires-Dist: fire (>=0.6.0,<0.7.0)
Project-URL: Bug Tracker, https://github.com/talk2bryan/vcf-generator/issues
Project-URL: Repository, https://github.com/talk2bryan/vcf-generator
